SequentialCircuits/DFlip/Dflip.v
module Dflip (
    input [31:0] D,
    input clk,reset,
    output reg [31:0]Q, notQ
    );

    always@(posedge clk)begin
        if(reset)begin
            Q<=32'b0;
            notQ<={32{1'b1}};
        end else begin
            Q<=D;
            notQ<=~D;
        end
    end

endmodule

SequentialCircuits/DFlip/DflipTB.sv
`include "Dflip.v"



module DflipTB();

    logic [31:0] D, Q, notQ;
    logic reset;
    logic clk;

    Dflip DUT (
        .D(D),
        .Q(Q),
        .clk(clk),
        .notQ(notQ),
        .reset(reset)
        );

    task testout();

        integer i, numtests;
        numtests = 100;

        for(i = 0;i<numtests;i=i+1) begin

            D = $urandom;
            #5;
            if(clk && D==Q) begin
                $display("Clk: %0d, d = %0b = q, notQ = %0b",clk,D,notQ);
            end else if(D!=Q) begin
                $display("Clk: %0d, d= %0b, q= %0b, q' = %0b",clk,D,Q,notQ);
            end
            else begin
                 $display("ERROR: Clk: %0d, d= %0b, q= %0b, q' = %0b",clk,D,Q,notQ);
            end

        end



    endtask

    task testreset();//Why does rest at posedge turn notQ into 0000001 but Q into 00000000??? wheres the one from?
        integer i, numtests;
        numtests =15;
        reset = 0;
        for(i=0;i<numtests;i = i+1) begin
            reset = #2 ~reset;
            D = $urandom;
            #5;
            if(clk && D==Q) begin
                $display("Clk: %0d, d = %0b = q, notQ = %0b",clk,D,notQ);
            end else if(D!=Q) begin
                $display("Clk: %0d, d= %0b, q= %0b, q' = %0b",clk,D,Q,notQ);
            end
            else begin
                 $display("ERROR: Clk: %0d, d= %0b, q= %0b, q' = %0b",clk,D,Q,notQ);
            end

        end
    endtask
    
    initial begin
        clk = 0;
        forever #10 clk = ~clk;

    end

    initial begin

        $dumpfile("dump.vcd");
        $dumpvars(1);   

        testout();

        testreset();


        

        $display("You will get that internship king!");
        $finish();
    end


endmodule

SequentialCircuits/DFlip/dump.vcd
$date
	Wed Jun 11 17:42:50 2025
$end
$version
	Icarus Verilog
$end
$timescale
	1s
$end
$scope module DflipTB $end
$var wire 32 ! notQ [31:0] $end
$var wire 32 " Q [31:0] $end
$var reg 32 # D [31:0] $end
$var reg 1 $ clk $end
$var reg 1 % reset $end
$upscope $end
$enddefinitions $end
$comment Show the parameter values. $end
$dumpall
$end
#0
$dumpvars
x%
0$
b10010010000101010011010100100100 #
bx "
bx !
$end
#5
b1000000100010010101111010000001 #
#10
b11111011011110110010100111110110 !
b100100001001101011000001001 "
b100100001001101011000001001 #
1$
#15
b110001111100000101011001100011 #
#20
b10000110101110010111101100001101 #
0$
#25
b11000110110111111001100110001101 #
#30
b11001101001111010111101110011010 !
b110010110000101000010001100101 "
b110010110000101000010001100101 #
1$
#35
b1001001101110101001000010010 #
#40
b10000000111100111110001100000001 #
0$
#45
b10000110110101111100110100001101 #
#50
b1000100110111000000111010001001 !
b10111011001000111111000101110110 "
b10111011001000111111000101110110 #
1$
#55
b10011110100011011100110100111101 #
#60
b11110110110101000101011111101101 #
0$
#65
b11000110001011011111011110001100 #
#70
b11000000100001011000000110 !
b11111100111111011110100111111001 "
b11111100111111011110100111111001 #
1$
#75
b1100011001101110010010011000110 #
#80
b1100010111101111000010011000101 #
0$
#85
b1010101000100111101001010101010 #
#90
b1101010100000000100000011010 !
b11110010101011111111011111100101 "
b11110010101011111111011111100101 #
1$
#95
b111011110100100111001001110111 #
#100
b1001001100101101011000010010 #
0$
#105
b11000111111011001101101110001111 #
#110
b110110011111001011000001101 !
b11111001001100000110100111110010 "
b11111001001100000110100111110010 #
1$
#115
b1100111011101101001011011001110 #
#120
b1110100000000000111101011101000 #
0$
#125
b1100010110010100100111011000101 #
#130
b1010001101001111011011010100011 !
b10101110010110000100100101011100 "
b10101110010110000100100101011100 #
1$
#135
b1011110100011100010100010111101 #
#140
b10110101010110101100000101101 #
0$
#145
b110010101001110010011001100101 #
#150
b11001110000100001001110110011100 !
b110001111011110110001001100011 "
b110001111011110110001001100011 #
1$
#155
b10000101011100111000011100001010 #
#160
b1000000001110110010001010000000 #
0$
#165
b10010000011001000010000100100000 #
#170
b101010100001111011101001010101 !
b11010101011110000100010110101010 "
b11010101011110000100010110101010 #
1$
#175
b1001110110011001100110010011101 #
#180
b1001011001000000011111010010110 #
0$
#185
b1001100000111011100000010011 #
#190
b11111001010000111100011111110010 !
b110101111000011100000001101 "
b110101111000011100000001101 #
1$
#195
b101001101001111101011001010011 #
#200
b10110101100111111101110101101011 #
0$
#205
b1101010101001100010101011010101 #
#210
b11111110111010001011010111111101 !
b1000101110100101000000010 "
b1000101110100101000000010 #
1$
#215
b1010111010101100011111010101110 #
#220
b10001110111111111110100100011101 #
0$
#225
b1100111110001010111001011001111 #
#230
b1101110011110111011011011011100 !
b10010001100001000100100100100011 "
b10010001100001000100100100100011 #
1$
#235
b10000101000010010110010100001010 #
#240
b1100101011100110000101011001010 #
0$
#245
b11110001100010100110000111100 #
#250
b110100101110100001000001101 !
b11111001011010001011110111110010 "
b11111001011010001011110111110010 #
1$
#255
b11000101001011100110000110001010 #
#260
b10100000110001001011001101000001 #
0$
#265
b1101100010010110011010011011000 #
#270
b1000011110111110000110010000111 !
b10111100001000001111001101111000 "
b10111100001000001111001101111000 #
1$
#275
b1000100100010100001001010001001 #
#280
b11110101110001010000110111101011 #
0$
#285
b11011011000000100110010110110110 #
#290
b11100101101000000011000111001 !
b11100011010010111111100111000110 "
b11100011010010111111100111000110 #
1$
#295
b11010111000101010001001110101110 #
#300
b1011110011101010000001010111100 #
0$
#305
b10010101000011111101110100101010 #
#310
b11111010001010000110010111110100 !
b101110101111001101000001011 "
b101110101111001101000001011 #
1$
#315
b111000100101111011111001110001 #
#320
b11000010111100100100000110000101 #
0$
#325
b10100111111100100101010101001111 #
#330
b11100010001100111001111111000100 !
b11101110011000110000000111011 "
b11101110011000110000000111011 #
1$
#335
b10011101000001100011001100111010 #
#340
b111111001000110011001001111110 #
0$
#345
b10001010101010100100101100010101 #
#350
b111001001100110010000001110 !
b11111000110110011001101111110001 "
b11111000110110011001101111110001 #
1$
#355
b11101100100111000100101111011001 #
#360
b10110001001000110000011101100010 #
0$
#365
b10100110001101011111101101001100 #
#370
b110000010111101010101001100000 !
b11001111101000010101010110011111 "
b11001111101000010101010110011111 #
1$
#375
b11000111101110011010000110001111 #
#380
b11111100011011011010100111111000 #
0$
#385
b1011011110011010110000010110111 #
#390
b10110000001110111010100101100000 !
b1001111110001000101011010011111 "
b1001111110001000101011010011111 #
1$
#395
b101110011111011001010001011100 #
#400
b101101110010111100000001011011 #
0$
#405
b11000100110111100011011110001001 #
#410
b11011011010100011100110110110110 !
b100100101011100011001001001001 "
b100100101011100011001001001001 #
1$
#415
b1101000001000110011111011010000 #
#420
b1101011111111101100000011010111 #
0$
#425
b101000110001111111110001010001 #
#430
b110100110111101101000001101001 !
b11001011001000010010111110010110 "
b11001011001000010010111110010110 #
1$
#435
b10000110000111010111111100001100 #
#440
b1100001001011001100111011000010 #
0$
#445
b11100100010101111110110111001000 #
#450
b11000100011111011010010110001000 !
b111011100000100101101001110111 "
b111011100000100101101001110111 #
1$
#455
b10011110111100101110110100111101 #
#460
b10001001000011001101101100010010 #
0$
#465
b111111000001010000000001111110 #
#470
b1001001000110100111111010010010 !
b10110110111001011000000101101101 "
b10110110111001011000000101101101 #
1$
#475
b10011100110110011110011100111001 #
#480
b10001111110100101000111100011111 #
0$
#485
b1101001111010111111011011010011 #
#490
b111101001001101101000001111010 !
b11000010110110010010111110000101 "
b11000010110110010010111110000101 #
1$
#495
b111100000101001000100001111000 #
#500
0%
0$
#502
b10101101110110100101100101011011 #
1%
#509
b10100100100010110100101101001001 #
0%
#510
b1011011011101001011010010110110 !
b10100100100010110100101101001001 "
1$
#516
b11111111100101010111000111111 #
1%
#520
0$
#523
b10010101000011001010111100101010 #
0%
#530
b11111111111111111111111111111111 !
b0 "
b10101100000101010110001101011000 #
1%
1$
#537
b1000011001111110011100010000110 #
0%
#540
0$
#544
b1000111000110100000110010001110 #
1%
#550
1$
#551
b1001110001011111111001010011100 #
0%
#558
b11111101001101011001100111111010 #
1%
#560
0$
#565
b10011011111011011110000100110 #
0%
#570
b11101100100000100100001111011001 !
b10011011111011011110000100110 "
1$
#572
b10111001100101100001011101110011 #
1%
#579
b1010001100010111011010010100011 #
0%
#580
0$
#586
b10111100110011010100000101111 #
1%
#590
b11111111111111111111111111111111 !
b0 "
1$
#593
b1011001110100101001001010110011 #
0%
#600
b101111110110000101011001011111 #
1%
0$
