RippleCarry/8bit_RippleCarry.v
// Code your design here


module HalfAdder( input	x1,
                 		x2,
                 output sum,
                 carry);

  assign sum = x1^x2;
  assign carry = x1&x2;
  
endmodule

module FullAdder(input  x1,
                 		x2,
                 		cin,
                 output cout,
                 		sum);
  
  wire w1,w2,w3;
  
  HalfAdder HA1(.x1(x1),
                .x2(x2),
                .sum(w2),
                .carry(w1));
  
  HalfAdder HA2(.x1(w2),
                .x2(cin),
                .sum(sum),
                .carry(w3));
  
  assign cout = w1|w3;
  
               
endmodule
//8-bit ripple carry!
module RippleCarry(input [7:0] x1,
                   [7:0] x2,
                   cin,
                   output cout,
                   [7:0] y);
  
  wire [6:0] w_cin;
  //Create first Adder
  FullAdder FA_0 (.x1(x1[0]),
                .x2(x2[0]),
                .cin(cin),
                .cout(w_cin[0])
                  .sum(y[0]));
  //Create last Adder
  FullAdder FA_7 (.x1(x1[7]),
                  .x2(x2[7]),
                  .cin(w_cin[6]),
                  .cout(cout)
                  .sum(y[7]));
  
  
  genvar i;
  
  generate
    for(i=1;i<7;i=i+1) begin
      FullAdder FA (.x1(x1[i]),
                    .x2(x2[i]),
                    .cin(w_cin[i-1]),//How to assign cins and couts in an algorithmic method?
                    .cout(i)
                    .sum(y[i]));
    end
  endgenerate
  
  
  
  
endmodule

RippleCarry/RippleCarry_test.sv
// Code your testbench here
// or browse Examples
// Code your testbench here
// or browse Examples

`include "8bit_RippleCarry.v"
module tb_FA();
  
  
  reg [7:0]x1;
  reg [7:0]x2;
  reg cin;
  reg cin_2;
  
  wire [7:0]sum;
  wire cout;
  
  RippleCarry DUT (.x1(x1),
                 .x2(x2),
                 .cin(cin),
                 .cout(cout),
                 .y(sum));

  
  
  task show;
    begin
      $display("Time: %t,%d + %d => sum= %d, cout= %d,cin=%d",
               $time,x1,x2,sum,cout,cin);
    end
  endtask
  
  task check_nums(input cin_local);
  	integer i,j;
    begin
    	cin = cin_local;
      	
   		
    
      //solution:
      	for(i=0;i<256;i=i+1) begin
        	x1=i;
        	for(j=0;j<256;j=j+1) begin
        		x2=j;
              	#5
          		show;
        	
        	end
     	end
      
      
      
    end
  endtask
  
  initial begin
    
    $dumpfile("dump.vcd");
    $dumpvars(1);
    
    x1=0;
    x2=0;
    cin=0;
    
    check_nums(0);
    
    check_nums(1);
    
    $finish;
  end
  
endmodule

RippleCarry/dump.vcd
$date
	Sat May 31 17:13:09 2025
$end
$version
	Icarus Verilog
$end
$timescale
	1s
$end
$scope module tb_FA $end
$var wire 8 ! sum [7:0] $end
$var wire 1 " cout $end
$var reg 1 # cin $end
$var reg 8 $ x1 [7:0] $end
$var reg 8 % x2 [7:0] $end
$upscope $end
$enddefinitions $end
$comment Show the parameter values. $end
$dumpall
$end
#0
$dumpvars
b0 %
b0 $
0#
0"
b0 !
$end
#5
b1 !
b1 %
#10
b10 !
b10 %
#15
b11 !
b11 %
#20
b100 !
b100 %
#25
b101 !
b101 %
#30
b110 !
b110 %
#35
b111 !
b111 %
#40
b1000 !
b1000 %
#45
b1001 !
b1001 %
#50
b1010 !
b1010 %
#55
b1011 !
b1011 %
#60
b1100 !
b1100 %
#65
b1101 !
b1101 %
#70
b1110 !
b1110 %
#75
b1111 !
b1111 %
#80
b10000 !
b10000 %
#85
b10001 !
b10001 %
#90
b10010 !
b10010 %
#95
b10011 !
b10011 %
#100
b10100 !
b10100 %
#105
b10101 !
b10101 %
#110
b10110 !
b10110 %
#115
b10111 !
b10111 %
#120
b11000 !
b11000 %
#125
b11001 !
b11001 %
#130
b11010 !
b11010 %
#135
b11011 !
b11011 %
#140
b11100 !
b11100 %
#145
b11101 !
b11101 %
#150
b11110 !
b11110 %
#155
b11111 !
b11111 %
#160
b100000 !
b100000 %
#165
b100001 !
b100001 %
#170
b100010 !
b100010 %
#175
b100011 !
b100011 %
#180
b100100 !
b100100 %
#185
b100101 !
b100101 %
#190
b100110 !
b100110 %
#195
b100111 !
b100111 %
#200
b101000 !
b101000 %
#205
b101001 !
b101001 %
#210
b101010 !
b101010 %
#215
b101011 !
b101011 %
#220
b101100 !
b101100 %
#225
b101101 !
b101101 %
#230
b101110 !
b101110 %
#235
b101111 !
b101111 %
#240
b110000 !
b110000 %
#245
b110001 !
b110001 %
#250
b110010 !
b110010 %
#255
b110011 !
b110011 %
#260
b110100 !
b110100 %
#265
b110101 !
b110101 %
#270
b110110 !
b110110 %
#275
b110111 !
b110111 %
#280
b111000 !
b111000 %
#285
b111001 !
b111001 %
#290
b111010 !
b111010 %
#295
b111011 !
b111011 %
#300
b111100 !
b111100 %
#305
b111101 !
b111101 %
#310
b111110 !
b111110 %
#315
b111111 !
b111111 %
#320
b1000000 !
b1000000 %
#325
b1000001 !
b1000001 %
#330
b1000010 !
b1000010 %
#335
b1000011 !
b1000011 %
#340
b1000100 !
b1000100 %
#345
b1000101 !
b1000101 %
#350
b1000110 !
b1000110 %
#355
b1000111 !
b1000111 %
#360
b1001000 !
b1001000 %
#365
b1001001 !
b1001001 %
#370
b1001010 !
b1001010 %
#375
b1001011 !
b1001011 %
#380
b1001100 !
b1001100 %
#385
b1001101 !
b1001101 %
#390
b1001110 !
b1001110 %
#395
b1001111 !
b1001111 %
#400
b1010000 !
b1010000 %
#405
b1010001 !
b1010001 %
#410
b1010010 !
b1010010 %
#415
b1010011 !
b1010011 %
#420
b1010100 !
b1010100 %
#425
b1010101 !
b1010101 %
#430
b1010110 !
b1010110 %
#435
b1010111 !
b1010111 %
#440
b1011000 !
b1011000 %
#445
b1011001 !
b1011001 %
#450
b1011010 !
b1011010 %
#455
b1011011 !
b1011011 %
#460
b1011100 !
b1011100 %
#465
b1011101 !
b1011101 %
#470
b1011110 !
b1011110 %
#475
b1011111 !
b1011111 %
#480
b1100000 !
b1100000 %
#485
b1100001 !
b1100001 %
#490
b1100010 !
b1100010 %
#495
b1100011 !
b1100011 %
#500
b1100100 !
b1100100 %
#505
b1100101 !
b1100101 %
#510
b1100110 !
b1100110 %
#515
b1100111 !
b1100111 %
#520
b1101000 !
b1101000 %
#525
b1101001 !
b1101001 %
#530
b1101010 !
b1101010 %
#535
b1101011 !
b1101011 %
#540
b1101100 !
b1101100 %
#545
b1101101 !
b1101101 %
#550
b1101110 !
b1101110 %
#555
b1101111 !
b1101111 %
#560
b1110000 !
b1110000 %
#565
b1110001 !
b1110001 %
#570
b1110010 !
b1110010 %
#575
b1110011 !
b1110011 %
#580
b1110100 !
b1110100 %
#585
b1110101 !
b1110101 %
#590
b1110110 !
b1110110 %
#595
b1110111 !
b1110111 %
#600
b1111000 !
b1111000 %
#605
b1111001 !
b1111001 %
#610
b1111010 !
b1111010 %
#615
b1111011 !
b1111011 %
#620
b1111100 !
b1111100 %
#625
b1111101 !
b1111101 %
#630
b1111110 !
b1111110 %
#635
b1111111 !
b1111111 %
#640
b10000000 !
b10000000 %
#645
b10000001 !
b10000001 %
#650
b10000010 !
b10000010 %
#655
b10000011 !
b10000011 %
#660
b10000100 !
b10000100 %
#665
b10000101 !
b10000101 %
#670
b10000110 !
b10000110 %
#675
b10000111 !
b10000111 %
#680
b10001000 !
b10001000 %
#685
b10001001 !
b10001001 %
#690
b10001010 !
b10001010 %
#695
b10001011 !
b10001011 %
#700
b10001100 !
b10001100 %
#705
b10001101 !
b10001101 %
#710
b10001110 !
b10001110 %
#715
b10001111 !
b10001111 %
#720
b10010000 !
b10010000 %
#725
b10010001 !
b10010001 %
#730
b10010010 !
b10010010 %
#735
b10010011 !
b10010011 %
#740
b10010100 !
b10010100 %
#745
b10010101 !
b10010101 %
#750
b10010110 !
b10010110 %
#755
b10010111 !
b10010111 %
#760
b10011000 !
b10011000 %
#765
b10011001 !
b10011001 %
#770
b10011010 !
b10011010 %
#775
b10011011 !
b10011011 %
#780
b10011100 !
b10011100 %
#785
b10011101 !
b10011101 %
#790
b10011110 !
b10011110 %
#795
b10011111 !
b10011111 %
#800
b10100000 !
b10100000 %
#805
b10100001 !
b10100001 %
#810
b10100010 !
b10100010 %
#815
b10100011 !
b10100011 %
#820
b10100100 !
b10100100 %
#825
b10100101 !
b10100101 %
#830
b10100110 !
b10100110 %
#835
b10100111 !
b10100111 %
#840
b10101000 !
b10101000 %
#845
b10101001 !
b10101001 %
#850
b10101010 !
b10101010 %
#855
b10101011 !
b10101011 %
#860
b10101100 !
b10101100 %
#865
b10101101 !
b10101101 %
#870
b10101110 !
b10101110 %
#875
b10101111 !
b10101111 %
#880
b10110000 !
b10110000 %
#885
b10110001 !
b10110001 %
#890
b10110010 !
b10110010 %
#895
b10110011 !
b10110011 %
#900
b10110100 !
b10110100 %
#905
b10110101 !
b10110101 %
#910
b10110110 !
b10110110 %
#915
b10110111 !
b10110111 %
#920
b10111000 !
b10111000 %
#925
b10111001 !
b10111001 %
#930
b10111010 !
b10111010 %
#935
b10111011 !
b10111011 %
#940
b10111100 !
b10111100 %
#945
b10111101 !
b10111101 %
#950
b10111110 !
b10111110 %
#955
b10111111 !
b10111111 %
#960
b11000000 !
b11000000 %
#965
b11000001 !
b11000001 %
#970
b11000010 !
b11000010 %
#975
b11000011 !
b11000011 %
#980
b11000100 !
b11000100 %
#985
b11000101 !
b11000101 %
#990
b11000110 !
b11000110 %
#995
b11000111 !
b11000111 %
#1000
b11001000 !
b11001000 %
#1005
b11001001 !
b11001001 %
#1010
b11001010 !
b11001010 %
#1015
b11001011 !
b11001011 %
#1020
b11001100 !
b11001100 %
#1025
b11001101 !
b11001101 %
#1030
b11001110 !
b11001110 %
#1035
b11001111 !
b11001111 %
#1040
b11010000 !
b11010000 %
#1045
b11010001 !
b11010001 %
#1050
b11010010 !
b11010010 %
#1055
b11010011 !
b11010011 %
#1060
b11010100 !
b11010100 %
#1065
b11010101 !
b11010101 %
#1070
b11010110 !
b11010110 %
#1075
b11010111 !
b11010111 %
#1080
b11011000 !
b11011000 %
#1085
b11011001 !
b11011001 %
#1090
b11011010 !
b11011010 %
#1095
b11011011 !
b11011011 %
#1100
b11011100 !
b11011100 %
#1105
b11011101 !
b11011101 %
#1110
b11011110 !
b11011110 %
#1115
b11011111 !
b11011111 %
#1120
b11100000 !
b11100000 %
#1125
b11100001 !
b11100001 %
#1130
b11100010 !
b11100010 %
#1135
b11100011 !
b11100011 %
#1140
b11100100 !
b11100100 %
#1145
b11100101 !
b11100101 %
#1150
b11100110 !
b11100110 %
#1155
b11100111 !
b11100111 %
#1160
b11101000 !
b11101000 %
#1165
b11101001 !
b11101001 %
#1170
b11101010 !
b11101010 %
#1175
b11101011 !
b11101011 %
#1180
b11101100 !
b11101100 %
#1185
b11101101 !
b11101101 %
#1190
b11101110 !
b11101110 %
#1195
b11101111 !
b11101111 %
#1200
b11110000 !
b11110000 %
#1205
b11110001 !
b11110001 %
#1210
b11110010 !
b11110010 %
#1215
b11110011 !
b11110011 %
#1220
b11110100 !
b11110100 %
#1225
b11110101 !
b11110101 %
#1230
b11110110 !
b11110110 %
#1235
b11110111 !
b11110111 %
#1240
b11111000 !
b11111000 %
#1245
b11111001 !
b11111001 %
#1250
b11111010 !
b11111010 %
#1255
b11111011 !
b11111011 %
#1260
b11111100 !
b11111100 %
#1265
b11111101 !
b11111101 %
#1270
b11111110 !
b11111110 %
#1275
b11111111 !
b11111111 %
#1280
b1 !
b0 %
b1 $
#1285
b10 !
b1 %
#1290
b11 !
b10 %
#1295
b100 !
b11 %
#1300
b101 !
b100 %
#1305
b110 !
b101 %
#1310
b111 !
b110 %
#1315
b1000 !
b111 %
#1320
b1001 !
b1000 %
#1325
b1010 !
b1001 %
#1330
b1011 !
b1010 %
#1335
b1100 !
b1011 %
#1340
b1101 !
b1100 %
#1345
b1110 !
b1101 %
#1350
b1111 !
b1110 %
#1355
b10000 !
b1111 %
#1360
b10001 !
b10000 %
#1365
b10010 !
b10001 %
#1370
b10011 !
b10010 %
#1375
b10100 !
b10011 %
#1380
b10101 !
b10100 %
#1385
b10110 !
b10101 %
#1390
b10111 !
b10110 %
#1395
b11000 !
b10111 %
#1400
b11001 !
b11000 %
#1405
b11010 !
b11001 %
#1410
b11011 !
b11010 %
#1415
b11100 !
b11011 %
#1420
b11101 !
b11100 %
#1425
b11110 !
b11101 %
#1430
b11111 !
b11110 %
#1435
b100000 !
b11111 %
#1440
b100001 !
b100000 %
#1445
b100010 !
b100001 %
#1450
b100011 !
b100010 %
#1455
b100100 !
b100011 %
#1460
b100101 !
b100100 %
#1465
b100110 !
b100101 %
#1470
b100111 !
b100110 %
#1475
b101000 !
b100111 %
#1480
b101001 !
b101000 %
#1485
b101010 !
b101001 %
#1490
b101011 !
b101010 %
#1495
b101100 !
b101011 %
#1500
b101101 !
b101100 %
#1505
b101110 !
b101101 %
#1510
b101111 !
b101110 %
#1515
b110000 !
b101111 %
#1520
b110001 !
b110000 %
#1525
b110010 !
b110001 %
#1530
b110011 !
b110010 %
#1535
b110100 !
b110011 %
#1540
b110101 !
b110100 %
#1545
b110110 !
b110101 %
#1550
b110111 !
b110110 %
#1555
b111000 !
b110111 %
#1560
b111001 !
b111000 %
#1565
b111010 !
b111001 %
#1570
b111011 !
b111010 %
#1575
b111100 !
b111011 %
#1580
b111101 !
b111100 %
#1585
b111110 !
b111101 %
#1590
b111111 !
b111110 %
#1595
b1000000 !
b111111 %
#1600
b1000001 !
b1000000 %
#1605
b1000010 !
b1000001 %
#1610
b1000011 !
b1000010 %
#1615
b1000100 !
b1000011 %
#1620
b1000101 !
b1000100 %
#1625
b1000110 !
b1000101 %
#1630
b1000111 !
b1000110 %
#1635
b1001000 !
b1000111 %
#1640
b1001001 !
b1001000 %
#1645
b1001010 !
b1001001 %
#1650
b1001011 !
b1001010 %
#1655
b1001100 !
b1001011 %
#1660
b1001101 !
b1001100 %
#1665
b1001110 !
b1001101 %
#1670
b1001111 !
b1001110 %
#1675
b1010000 !
b1001111 %
#1680
b1010001 !
b1010000 %
#1685
b1010010 !
b1010001 %
#1690
b1010011 !
b1010010 %
#1695
b1010100 !
b1010011 %
#1700
b1010101 !
b1010100 %
#1705
b1010110 !
b1010101 %
#1710
b1010111 !
b1010110 %
#1715
b1011000 !
b1010111 %
#1720
b1011001 !
b1011000 %
#1725
b1011010 !
b1011001 %
#1730
b1011011 !
b1011010 %
#1735
b1011100 !
b1011011 %
#1740
b1011101 !
b1011100 %
#1745
b1011110 !
b1011101 %
#1750
b1011111 !
b1011110 %
#1755
b1100000 !
b1011111 %
#1760
b1100001 !
b1100000 %
#1765
b1100010 !
b1100001 %
#1770
b1100011 !
b1100010 %
#1775
b1100100 !
b1100011 %
#1780
b1100101 !
b1100100 %
#1785
b1100110 !
b1100101 %
#1790
b1100111 !
b1100110 %
#1795
b1101000 !
b1100111 %
#1800
b1101001 !
b1101000 %
#1805
b1101010 !
b1101001 %
#1810
b1101011 !
b1101010 %
#1815
b1101100 !
b1101011 %
#1820
b1101101 !
b1101100 %
#1825
b1101110 !
b1101101 %
#1830
b1101111 !
b1101110 %
#1835
b1110000 !
b1101111 %
#1840
b1110001 !
b1110000 %
#1845
b1110010 !
b1110001 %
#1850
b1110011 !
b1110010 %
#1855
b1110100 !
b1110011 %
#1860
b1110101 !
b1110100 %
#1865
b1110110 !
b1110101 %
#1870
b1110111 !
b1110110 %
#1875
b1111000 !
b1110111 %
#1880
b1111001 !
b1111000 %
#1885
b1111010 !
b1111001 %
#1890
b1111011 !
b1111010 %
#1895
b1111100 !
b1111011 %
#1900
b1111101 !
b1111100 %
#1905
b1111110 !
b1111101 %
#1910
b1111111 !
b1111110 %
#1915
b10000000 !
b1111111 %
#1920
0"
b10000001 !
b10000000 %
#1925
b10000010 !
b10000001 %
#1930
b10000011 !
b10000010 %
#1935
b10000100 !
b10000011 %
#1940
b10000101 !
b10000100 %
#1945
b10000110 !
b10000101 %
#1950
b10000111 !
b10000110 %
#1955
b10001000 !
b10000111 %
#1960
b10001001 !
b10001000 %
#1965
b10001010 !
b10001001 %
#1970
b10001011 !
b10001010 %
#1975
b10001100 !
b10001011 %
#1980
b10001101 !
b10001100 %
#1985
b10001110 !
b10001101 %
#1990
b10001111 !
b10001110 %
#1995
b10010000 !
b10001111 %
#2000
b10010001 !
b10010000 %
#2005
b10010010 !
b10010001 %
#2010
b10010011 !
b10010010 %
#2015
b10010100 !
b10010011 %
#2020
b10010101 !
b10010100 %
#2025
b10010110 !
b10010101 %
#2030
b10010111 !
b10010110 %
#2035
b10011000 !
b10010111 %
#2040
b10011001 !
b10011000 %
#2045
b10011010 !
b10011001 %
#2050
b10011011 !
b10011010 %
#2055
b10011100 !
b10011011 %
#2060
b10011101 !
b10011100 %
#2065
b10011110 !
b10011101 %
#2070
b10011111 !
b10011110 %
#2075
b10100000 !
b10011111 %
#2080
b10100001 !
b10100000 %
#2085
b10100010 !
b10100001 %
#2090
b10100011 !
b10100010 %
#2095
b10100100 !
b10100011 %
#2100
b10100101 !
b10100100 %
#2105
b10100110 !
b10100101 %
#2110
b10100111 !
b10100110 %
#2115
b10101000 !
b10100111 %
#2120
b10101001 !
b10101000 %
#2125
b10101010 !
b10101001 %
#2130
b10101011 !
b10101010 %
#2135
b10101100 !
b10101011 %
#2140
b10101101 !
b10101100 %
#2145
b10101110 !
b10101101 %
#2150
b10101111 !
b10101110 %
#2155
b10110000 !
b10101111 %
#2160
b10110001 !
b10110000 %
#2165
b10110010 !
b10110001 %
#2170
b10110011 !
b10110010 %
#2175
b10110100 !
b10110011 %
#2180
b10110101 !
b10110100 %
#2185
b10110110 !
b10110101 %
#2190
b10110111 !
b10110110 %
#2195
b10111000 !
b10110111 %
#2200
b10111001 !
b10111000 %
#2205
b10111010 !
b10111001 %
#2210
b10111011 !
b10111010 %
#2215
b10111100 !
b10111011 %
#2220
b10111101 !
b10111100 %
#2225
b10111110 !
b10111101 %
#2230
b10111111 !
b10111110 %
#2235
b11000000 !
b10111111 %
#2240
0"
b11000001 !
b11000000 %
#2245
b11000010 !
b11000001 %
#2250
b11000011 !
b11000010 %
#2255
b11000100 !
b11000011 %
#2260
b11000101 !
b11000100 %
#2265
b11000110 !
b11000101 %
#2270
b11000111 !
b11000110 %
#2275
b11001000 !
b11000111 %
#2280
b11001001 !
b11001000 %
#2285
b11001010 !
b11001001 %
#2290
b11001011 !
b11001010 %
#2295
b11001100 !
b11001011 %
#2300
b11001101 !
b11001100 %
#2305
b11001110 !
b11001101 %
#2310
b11001111 !
b11001110 %
#2315
b11010000 !
b11001111 %
#2320
b11010001 !
b11010000 %
#2325
b11010010 !
b11010001 %
#2330
b11010011 !
b11010010 %
#2335
b11010100 !
b11010011 %
#2340
b11010101 !
b11010100 %
#2345
b11010110 !
b11010101 %
#2350
b11010111 !
b11010110 %
#2355
b11011000 !
b11010111 %
#2360
b11011001 !
b11011000 %
#2365
b11011010 !
b11011001 %
#2370
b11011011 !
b11011010 %
#2375
b11011100 !
b11011011 %
#2380
b11011101 !
b11011100 %
#2385
b11011110 !
b11011101 %
#2390
b11011111 !
b11011110 %
#2395
b11100000 !
b11011111 %
#2400
0"
b11100001 !
b11100000 %
#2405
b11100010 !
b11100001 %
#2410
b11100011 !
b11100010 %
#2415
b11100100 !
b11100011 %
#2420
b11100101 !
b11100100 %
#2425
b11100110 !
b11100101 %
#2430
b11100111 !
b11100110 %
#2435
b11101000 !
b11100111 %
#2440
b11101001 !
b11101000 %
#2445
b11101010 !
b11101001 %
#2450
b11101011 !
b11101010 %
#2455
b11101100 !
b11101011 %
#2460
b11101101 !
b11101100 %
#2465
b11101110 !
b11101101 %
#2470
b11101111 !
b11101110 %
#2475
b11110000 !
b11101111 %
#2480
0"
b11110001 !
b11110000 %
#2485
b11110010 !
b11110001 %
#2490
b11110011 !
b11110010 %
#2495
b11110100 !
b11110011 %
#2500
b11110101 !
b11110100 %
#2505
b11110110 !
b11110101 %
#2510
b11110111 !
b11110110 %
#2515
b11111000 !
b11110111 %
#2520
0"
b11111001 !
b11111000 %
#2525
b11111010 !
b11111001 %
#2530
b11111011 !
b11111010 %
#2535
b11111100 !
b11111011 %
#2540
0"
b11111101 !
b11111100 %
#2545
b11111110 !
b11111101 %
#2550
0"
b11111111 !
b11111110 %
#2555
1"
b0 !
b11111111 %
#2560
0"
b10 !
b0 %
b10 $
#2565
b11 !
b1 %
#2570
b100 !
b10 %
#2575
b101 !
b11 %
#2580
b110 !
b100 %
#2585
b111 !
b101 %
#2590
b1000 !
b110 %
#2595
b1001 !
b111 %
#2600
b1010 !
b1000 %
#2605
b1011 !
b1001 %
#2610
b1100 !
b1010 %
#2615
b1101 !
b1011 %
#2620
b1110 !
b1100 %
#2625
b1111 !
b1101 %
#2630
b10000 !
b1110 %
#2635
b10001 !
b1111 %
#2640
b10010 !
b10000 %
#2645
b10011 !
b10001 %
#2650
b10100 !
b10010 %
#2655
b10101 !
b10011 %
#2660
b10110 !
b10100 %
#2665
b10111 !
b10101 %
#2670
b11000 !
b10110 %
#2675
b11001 !
b10111 %
#2680
b11010 !
b11000 %
#2685
b11011 !
b11001 %
#2690
b11100 !
b11010 %
#2695
b11101 !
b11011 %
#2700
b11110 !
b11100 %
#2705
b11111 !
b11101 %
#2710
b100000 !
b11110 %
#2715
b100001 !
b11111 %
#2720
b100010 !
b100000 %
#2725
b100011 !
b100001 %
#2730
b100100 !
b100010 %
#2735
b100101 !
b100011 %
#2740
b100110 !
b100100 %
#2745
b100111 !
b100101 %
#2750
b101000 !
b100110 %
#2755
b101001 !
b100111 %
#2760
b101010 !
b101000 %
#2765
b101011 !
b101001 %
#2770
b101100 !
b101010 %
#2775
b101101 !
b101011 %
#2780
b101110 !
b101100 %
#2785
b101111 !
b101101 %
#2790
b110000 !
b101110 %
#2795
b110001 !
b101111 %
#2800
b110010 !
b110000 %
#2805
b110011 !
b110001 %
#2810
b110100 !
b110010 %
#2815
b110101 !
b110011 %
#2820
b110110 !
b110100 %
#2825
b110111 !
b110101 %
#2830
b111000 !
b110110 %
#2835
b111001 !
b110111 %
#2840
b111010 !
b111000 %
#2845
b111011 !
b111001 %
#2850
b111100 !
b111010 %
#2855
b111101 !
b111011 %
#2860
b111110 !
b111100 %
#2865
b111111 !
b111101 %
#2870
b1000000 !
b111110 %
#2875
b1000001 !
b111111 %
#2880
b1000010 !
b1000000 %
#2885
b1000011 !
b1000001 %
#2890
b1000100 !
b1000010 %
#2895
b1000101 !
b1000011 %
#2900
b1000110 !
b1000100 %
#2905
b1000111 !
b1000101 %
#2910
b1001000 !
b1000110 %
#2915
b1001001 !
b1000111 %
#2920
b1001010 !
b1001000 %
#2925
b1001011 !
b1001001 %
#2930
b1001100 !
b1001010 %
#2935
b1001101 !
b1001011 %
#2940
b1001110 !
b1001100 %
#2945
b1001111 !
b1001101 %
#2950
b1010000 !
b1001110 %
#2955
b1010001 !
b1001111 %
#2960
b1010010 !
b1010000 %
#2965
b1010011 !
b1010001 %
#2970
b1010100 !
b1010010 %
#2975
b1010101 !
b1010011 %
#2980
b1010110 !
b1010100 %
#2985
b1010111 !
b1010101 %
#2990
b1011000 !
b1010110 %
#2995
b1011001 !
b1010111 %
#3000
b1011010 !
b1011000 %
#3005
b1011011 !
b1011001 %
#3010
b1011100 !
b1011010 %
#3015
b1011101 !
b1011011 %
#3020
b1011110 !
b1011100 %
#3025
b1011111 !
b1011101 %
#3030
b1100000 !
b1011110 %
#3035
b1100001 !
b1011111 %
#3040
b1100010 !
b1100000 %
#3045
b1100011 !
b1100001 %
#3050
b1100100 !
b1100010 %
#3055
b1100101 !
b1100011 %
#3060
b1100110 !
b1100100 %
#3065
b1100111 !
b1100101 %
#3070
b1101000 !
b1100110 %
#3075
b1101001 !
b1100111 %
#3080
b1101010 !
b1101000 %
#3085
b1101011 !
b1101001 %
#3090
b1101100 !
b1101010 %
#3095
b1101101 !
b1101011 %
#3100
b1101110 !
b1101100 %
#3105
b1101111 !
b1101101 %
#3110
b1110000 !
b1101110 %
#3115
b1110001 !
b1101111 %
#3120
b1110010 !
b1110000 %
#3125
b1110011 !
b1110001 %
#3130
b1110100 !
b1110010 %
#3135
b1110101 !
b1110011 %
#3140
b1110110 !
b1110100 %
#3145
b1110111 !
b1110101 %
#3150
b1111000 !
b1110110 %
#3155
b1111001 !
b1110111 %
#3160
b1111010 !
b1111000 %
#3165
b1111011 !
b1111001 %
#3170
b1111100 !
b1111010 %
#3175
b1111101 !
b1111011 %
#3180
b1111110 !
b1111100 %
#3185
b1111111 !
b1111101 %
#3190
b10000000 !
b1111110 %
#3195
b10000001 !
b1111111 %
#3200
0"
b10000010 !
b10000000 %
#3205
b10000011 !
b10000001 %
#3210
b10000100 !
b10000010 %
#3215
b10000101 !
b10000011 %
#3220
b10000110 !
b10000100 %
#3225
b10000111 !
b10000101 %
#3230
b10001000 !
b10000110 %
#3235
b10001001 !
b10000111 %
#3240
b10001010 !
b10001000 %
#3245
b10001011 !
b10001001 %
#3250
b10001100 !
b10001010 %
#3255
b10001101 !
b10001011 %
#3260
b10001110 !
b10001100 %
#3265
b10001111 !
b10001101 %
#3270
b10010000 !
b10001110 %
#3275
b10010001 !
b10001111 %
#3280
b10010010 !
b10010000 %
#3285
b10010011 !
b10010001 %
#3290
b10010100 !
b10010010 %
#3295
b10010101 !
b10010011 %
#3300
b10010110 !
b10010100 %
#3305
b10010111 !
b10010101 %
#3310
b10011000 !
b10010110 %
#3315
b10011001 !
b10010111 %
#3320
b10011010 !
b10011000 %
#3325
b10011011 !
b10011001 %
#3330
b10011100 !
b10011010 %
#3335
b10011101 !
b10011011 %
#3340
b10011110 !
b10011100 %
#3345
b10011111 !
b10011101 %
#3350
b10100000 !
b10011110 %
#3355
b10100001 !
b10011111 %
#3360
b10100010 !
b10100000 %
#3365
b10100011 !
b10100001 %
#3370
b10100100 !
b10100010 %
#3375
b10100101 !
b10100011 %
#3380
b10100110 !
b10100100 %
#3385
b10100111 !
b10100101 %
#3390
b10101000 !
b10100110 %
#3395
b10101001 !
b10100111 %
#3400
b10101010 !
b10101000 %
#3405
b10101011 !
b10101001 %
#3410
b10101100 !
b10101010 %
#3415
b10101101 !
b10101011 %
#3420
b10101110 !
b10101100 %
#3425
b10101111 !
b10101101 %
#3430
b10110000 !
b10101110 %
#3435
b10110001 !
b10101111 %
#3440
b10110010 !
b10110000 %
#3445
b10110011 !
b10110001 %
#3450
b10110100 !
b10110010 %
#3455
b10110101 !
b10110011 %
#3460
b10110110 !
b10110100 %
#3465
b10110111 !
b10110101 %
#3470
b10111000 !
b10110110 %
#3475
b10111001 !
b10110111 %
#3480
b10111010 !
b10111000 %
#3485
b10111011 !
b10111001 %
#3490
b10111100 !
b10111010 %
#3495
b10111101 !
b10111011 %
#3500
b10111110 !
b10111100 %
#3505
b10111111 !
b10111101 %
#3510
b11000000 !
b10111110 %
#3515
b11000001 !
b10111111 %
#3520
0"
b11000010 !
b11000000 %
#3525
b11000011 !
b11000001 %
#3530
b11000100 !
b11000010 %
#3535
b11000101 !
b11000011 %
#3540
b11000110 !
b11000100 %
#3545
b11000111 !
b11000101 %
#3550
b11001000 !
b11000110 %
#3555
b11001001 !
b11000111 %
#3560
b11001010 !
b11001000 %
#3565
b11001011 !
b11001001 %
#3570
b11001100 !
b11001010 %
#3575
b11001101 !
b11001011 %
#3580
b11001110 !
b11001100 %
#3585
b11001111 !
b11001101 %
#3590
b11010000 !
b11001110 %
#3595
b11010001 !
b11001111 %
#3600
b11010010 !
b11010000 %
#3605
b11010011 !
b11010001 %
#3610
b11010100 !
b11010010 %
#3615
b11010101 !
b11010011 %
#3620
b11010110 !
b11010100 %
#3625
b11010111 !
b11010101 %
#3630
b11011000 !
b11010110 %
#3635
b11011001 !
b11010111 %
#3640
b11011010 !
b11011000 %
#3645
b11011011 !
b11011001 %
#3650
b11011100 !
b11011010 %
#3655
b11011101 !
b11011011 %
#3660
b11011110 !
b11011100 %
#3665
b11011111 !
b11011101 %
#3670
b11100000 !
b11011110 %
#3675
b11100001 !
b11011111 %
#3680
0"
b11100010 !
b11100000 %
#3685
b11100011 !
b11100001 %
#3690
b11100100 !
b11100010 %
#3695
b11100101 !
b11100011 %
#3700
b11100110 !
b11100100 %
#3705
b11100111 !
b11100101 %
#3710
b11101000 !
b11100110 %
#3715
b11101001 !
b11100111 %
#3720
b11101010 !
b11101000 %
#3725
b11101011 !
b11101001 %
#3730
b11101100 !
b11101010 %
#3735
b11101101 !
b11101011 %
#3740
b11101110 !
b11101100 %
#3745
b11101111 !
b11101101 %
#3750
b11110000 !
b11101110 %
#3755
b11110001 !
b11101111 %
#3760
0"
b11110010 !
b11110000 %
#3765
b11110011 !
b11110001 %
#3770
b11110100 !
b11110010 %
#3775
b11110101 !
b11110011 %
#3780
b11110110 !
b11110100 %
#3785
b11110111 !
b11110101 %
#3790
b11111000 !
b11110110 %
#3795
b11111001 !
b11110111 %
#3800
0"
b11111010 !
b11111000 %
#3805
b11111011 !
b11111001 %
#3810
b11111100 !
b11111010 %
#3815
b11111101 !
b11111011 %
#3820
0"
b11111110 !
b11111100 %
#3825
b11111111 !
b11111101 %
#3830
1"
b0 !
b11111110 %
#3835
b1 !
b11111111 %
#3840
0"
b11 !
b0 %
b11 $
#3845
b100 !
b1 %
#3850
b101 !
b10 %
#3855
b110 !
b11 %
#3860
b111 !
b100 %
#3865
b1000 !
b101 %
#3870
b1001 !
b110 %
#3875
b1010 !
b111 %
#3880
b1011 !
b1000 %
#3885
b1100 !
b1001 %
#3890
b1101 !
b1010 %
#3895
b1110 !
b1011 %
#3900
b1111 !
b1100 %
#3905
b10000 !
b1101 %
#3910
b10001 !
b1110 %
#3915
b10010 !
b1111 %
#3920
b10011 !
b10000 %
#3925
b10100 !
b10001 %
#3930
b10101 !
b10010 %
#3935
b10110 !
b10011 %
#3940
b10111 !
b10100 %
