n_bit_add_sub/addsub.v

module AddSub #(parameter N =8) (input [N-1:0] x1,
                                  input [N-1:0] x2,
                                  input addSub,
                                  output [N-1:0] sum,
                                  output cout
                                  );

    reg [N:0] result;

    always @(*) begin
        if(addSub) begin
            result = x1 + (~x2 + 1);
        end else begin
            result = x1 + x2;
        end
        
    end
    assign cout = result[N];
    assign sum = result[N-1:0];

endmodule

n_bit_add_sub/addsubTB.sv
`ifndef N
    `define N 8
`endif




`include "addsub.v"

module addsubTB ();
    parameter N = `N;

    logic [N-1:0] x1;
    logic [N-1:0] x2;
    logic addsub;
    logic [N-1:0] sum;
    logic cout;
    logic [N:0] expected_result;


    AddSub #(N) DUT (
        .x1(x1),
        .x2(x2),
        .addSub(addsub),
        .sum(sum),
        .cout(cout)
    );



    task automatic testaddsub(input addsub_local);
        int num_tests =1000;
        addsub = addsub_local;
        
        $display("Beginning <addsub=%0d> Tests for %0dbits",addsub,N);

        for(int i=0;i<num_tests;i++) begin
            
            x1 = $urandom;
            x2 = $urandom;

            #1;
            if(addsub) begin
                expected_result = x1 - x2;
            end else begin
                expected_result = x1 + x2;
            end 

            if({cout, sum} !== expected_result) begin
                
                $display("Test %0d Failed: x1=%0h x2=%0h | DUT={%0b,%0h} Expected={%0b, %0h}",
                i, x1, x2, cout, sum, expected_result[N], expected_result[N-1:0]);
            end else begin
                $display("Test %0d PASSED", i);
            end    
        end

        $display("Testing Complete! ");

    endtask
    
    

    
    
    initial begin //main simulation

    $dumpfile("dump.vcd");
    $dumpvars(1);

    testaddsub(0);

    testaddsub(1);


    end


endmodule

CombinationalCircuits/n_bit_add_sub/dump.vcd
$date
	Mon Jun 02 20:18:20 2025
$end
$version
	Icarus Verilog
$end
$timescale
	1s
$end
$scope module addsubTB $end
$var wire 8 ! sum [7:0] $end
$var wire 1 " cout $end
$var parameter 32 # N $end
$var reg 1 $ addsub $end
$var reg 9 % expected_result [8:0] $end
$var reg 8 & x1 [7:0] $end
$var reg 8 ' x2 [7:0] $end
$upscope $end
$enddefinitions $end
$comment Show the parameter values. $end
$dumpall
b1000 #
$end
#0
$dumpvars
b10000001 '
b100100 &
bx %
0$
0"
b10100101 !
$end
#1
b1101100 !
b1100011 '
b1001 &
b10100101 %
#2
b10011010 !
b10001101 '
b1101 &
b1101100 %
#3
b1110111 !
b10010 '
b1100101 &
b10011010 %
#4
b1110 !
b1101 '
b1 &
b1110111 %
#5
b10110011 !
b111101 '
b1110110 &
b1110 %
#6
1"
b1111001 !
b10001100 '
b11101101 &
b10110011 %
#7
b10111111 !
b11000110 '
b11111001 &
b101111001 %
#8
b1101111 !
b10101010 '
b11000101 &
b110111111 %
#9
b1011100 !
b1110111 '
b11100101 &
b101101111 %
#10
0"
b10100001 !
b10001111 '
b10010 &
b101011100 %
#11
1"
b11000000 !
b11001110 '
b11110010 &
b10100001 %
#12
b10101101 !
b11000101 '
b11101000 &
b111000000 %
#13
b11001 !
b10111101 '
b1011100 &
b110101101 %
#14
0"
b10010010 !
b1100101 '
b101101 &
b100011001 %
#15
b1101101 !
b1010 '
b1100011 &
b10010010 %
#16
b10100000 !
b100000 '
b10000000 &
b1101101 %
#17
1"
b1000111 !
b10011101 '
b10101010 &
b10100000 %
#18
0"
b10101001 !
b10011 '
b10010110 &
b101000111 %
#19
b1100000 !
b1010011 '
b1101 &
b10101001 %
#20
1"
b1000000 !
b11010101 '
b1101011 &
b1100000 %
#21
0"
b10110000 !
b10101110 '
b10 &
b101000000 %
#22
b11101100 !
b11001111 '
b11101 &
b10110000 %
#23
b101101 !
b1010 '
b100011 &
b11101100 %
#24
1"
b110 !
b111100 '
b11001010 &
b101101 %
#25
b1111100 !
b10001010 '
b11110010 &
b100000110 %
#26
b11001 !
b11011000 '
b1000001 &
b101111100 %
#27
b1 !
b10001001 '
b1111000 &
b100011001 %
#28
b10100001 !
b10110110 '
b11101011 &
b100000001 %
#29
b1110100 !
b10101110 '
b11000110 &
b110100001 %
#30
0"
b11100110 !
b101010 '
b10111100 &
b101110100 %
#31
b1111100 !
b1110001 '
b1011 &
b11100110 %
#32
b11010100 !
b1001111 '
b10000101 &
b1111100 %
#33
b1110101 !
b111010 '
b111011 &
b11010100 %
#34
b10010011 !
b10101 '
b1111110 &
b1110101 %
#35
1"
b11001010 !
b11011001 '
b11110001 &
b10010011 %
#36
0"
b10101110 !
b1001100 '
b1100010 &
b111001010 %
#37
1"
b101110 !
b10001111 '
b10011111 &
b10101110 %
#38
b10101111 !
b10110111 '
b11111000 &
b100101110 %
#39
0"
b11111011 !
b1011100 '
b10011111 &
b110101111 %
#40
b11100100 !
b10001001 '
b1011011 &
b11111011 %
#41
1"
b11001 !
b11010000 '
b1001001 &
b11100100 %
#42
b101000 !
b1010001 '
b11010111 &
b100011001 %
#43
0"
b10100010 !
b1100 '
b10010110 &
b100101000 %
#44
1"
b10001010 !
b11001000 '
b11000010 &
b10100010 %
#45
0"
b10110100 !
b111101 '
b1110111 &
b110001010 %
#46
b10010000 !
b1111110 '
b10010 &
b10110100 %
#47
b10100110 !
b111001 '
b1101101 &
b10010000 %
#48
b11110010 !
b11010011 '
b11111 &
b10100110 %
#49
b11111101 !
b1111000 '
b10000101 &
b11110010 %
#50
b10100100 !
b1001001 '
b1011011 &
b11111101 %
#51
b1101001 !
b101010 '
b111111 &
b10100100 %
#52
b11011110 !
b10000110 '
b1011000 &
b1101001 %
#53
1"
b101010 !
b10011100 '
b10001110 &
b11011110 %
#54
b100000 !
b100110 '
b11111010 &
b100101010 %
#55
b10110 !
b10100011 '
b1110011 &
b100100000 %
#56
0"
b11100010 !
b10110011 '
b101111 &
b100010110 %
#57
b10100011 !
b1000100 '
b1011111 &
b11100010 %
#58
1"
b11000010 !
b11001011 '
b11110111 &
b10100011 %
#59
b1000000 !
b1011010 '
b11100110 &
b111000010 %
#60
b10110 !
b11101101 '
b101001 &
b101000000 %
#61
b111111 !
b1100101 '
b11011010 &
b100010110 %
#62
b10010100 !
b11011111 '
b10110101 &
b100111111 %
#63
0"
b10111101 !
b1000100 '
b1111001 &
b110010100 %
#64
b11111010 !
b101010 '
b11010000 &
b10111101 %
#65
b10111001 !
b1110 '
b10101011 &
b11111010 %
#66
1"
b1110110 !
b10011010 '
b11011100 &
b10111001 %
#67
b11000000 !
b11000011 '
b11111101 &
b101110110 %
#68
0"
b10100100 !
b1001110 '
b1010110 &
b111000000 %
#69
b1110001 !
b1010 '
b1100111 &
b10100100 %
#70
b11101110 !
b111000 '
b10110110 &
b1110001 %
#71
1"
b110001 !
b10111000 '
b1111001 &
b11101110 %
#72
b100111 !
b10010011 '
b10010100 &
b100110001 %
#73
0"
b1011101 !
b1011001 '
b100 &
b100100111 %
#74
1"
b101000 !
b1001101 '
b11011011 &
b1011101 %
#75
b1000110 !
b1101101 '
b11011001 &
b100101000 %
#76
b1000000 !
b11001010 '
b1110110 &
b101000110 %
#77
b1001011 !
b10010101 '
b10110110 &
b101000000 %
#78
0"
b1001010 !
b100 '
b1000110 &
b101001011 %
#79
1"
b1100000 !
b1101001 '
b11110111 &
b1001010 %
#80
b111100 !
b10001000 '
b10110100 &
b101100000 %
#81
0"
b1010101 !
b101101 '
b101000 &
b100111100 %
#82
b11110101 !
b101110 '
b11000111 &
b1010101 %
#83
b100100 !
b11100 '
b1000 &
b11110101 %
#84
1"
b100110 !
b101001 '
b11111101 &
b100100 %
#85
0"
b10100010 !
b10000110 '
b11100 &
b100100110 %
#86
1"
b10111 !
b111101 '
b11011010 &
b10100010 %
#87
0"
b11010110 !
b1110000 '
b1100110 &
b100010111 %
#88
1"
b101101 !
b10111010 '
b1110011 &
b11010110 %
#89
b1011000 !
b11111010 '
b1011110 &
b100101101 %
#90
0"
b11101111 !
b11010 '
b11010101 &
b101011000 %
#91
b11110000 !
b110111 '
b10111001 &
b11101111 %
#92
1"
b1010110 !
b11000000 '
b10010110 &
b11110000 %
#93
0"
b11011100 !
b10110110 '
b100110 &
b101010110 %
#94
1"
b1011001 !
b11011100 '
b1111101 &
b11011100 %
#95
0"
b11111110 !
b1111000 '
b10000110 &
b101011001 %
#96
1"
b1011001 !
b11011011 '
b1111110 &
b11111110 %
#97
b1001000 !
b1111001 '
b11001111 &
b101011001 %
#98
b1011011 !
b1100001 '
b11111010 &
b101001000 %
#99
0"
b10111000 !
b10100001 '
b10111 &
b101011011 %
#100
b11010110 !
b1010000 '
b10000110 &
b10111000 %
#101
1"
b101010 !
b110101 '
b11110101 &
b11010110 %
#102
0"
b11101010 !
b11000001 '
b101001 &
b100101010 %
#103
1"
b1011101 !
b10011000 '
b11000101 &
b11101010 %
#104
0"
b10111110 !
b1110011 '
b1001011 &
b101011101 %
#105
1"
b1110110 !
b10001010 '
b11101100 &
b10111110 %
#106
0"
b11110110 !
b10101000 '
b1001110 &
b101110110 %
#107
1"
b1001010 !
b10100001 '
b10101001 &
b11110110 %
#108
0"
b11110100 !
b11100110 '
b1110 &
b101001010 %
#109
b11001001 !
b101010 '
b10011111 &
b11110100 %
#110
b10110111 !
b10001101 '
b101010 &
b11001001 %
#111
b11010110 !
b111000 '
b10011110 &
b10110111 %
#112
1"
b1000001 !
b11001000 '
b1111001 &
b11010110 %
#113
0"
b11011101 !
b10011 '
b11001010 &
b101000001 %
#114
1"
b110010 !
b11000111 '
b1101011 &
b11011101 %
#115
b1110000 !
b10111010 '
b10110110 &
b100110010 %
#116
b1111101 !
b10111001 '
b11000100 &
b101110000 %
#117
b1000110 !
b10110100 '
b10010010 &
b101111101 %
#118
b101 !
b10000110 '
b1111111 &
b101000110 %
#119
b11101100 !
b11110010 '
b11111010 &
b100000101 %
#120
0"
b11101111 !
b10111101 '
b110010 &
b111101100 %
#121
1"
b1101000 !
b11100100 '
b10000100 &
b11101111 %
#122
b1110011 !
b10101001 '
b11001010 &
b101101000 %
#123
b101111 !
b10001110 '
b10100001 &
b101110011 %
#124
b110 !
b1011 '
b11111011 &
b100101111 %
#125
b10111000 !
b11001001 '
b11101111 &
b100000110 %
#126
0"
b10101011 !
b1110101 '
b110110 &
b110111000 %
#127
b11111010 !
b1101011 '
b10001111 &
b10101011 %
#128
1"
b110110 !
b10101110 '
b10001000 &
b11111010 %
#129
b101101 !
b10010010 '
b10011011 &
b100110110 %
#130
0"
b1010101 !
b101101 '
b101000 &
b100101101 %
#131
1"
b1101 !
b11000010 '
b1001011 &
b1010101 %
#132
0"
b101011 !
b1101 '
b11110 &
b100001101 %
#133
1"
b100 !
b11000 '
b11101100 &
b101011 %
#134
b1010111 !
b10000110 '
b11010001 &
b100000100 %
#135
0"
b1111100 !
b111011 '
b1000001 &
b101010111 %
#136
1"
b101011 !
b1010011 '
b11011000 &
b1111100 %
#137
0"
b10110001 !
b1011011 '
b1010110 &
b100101011 %
#138
b11100110 !
b100 '
b11100010 &
b10110001 %
#139
1"
b1001011 !
b11011000 '
b1110011 &
b11100110 %
#140
0"
b11001010 !
b10111000 '
b10010 &
b101001011 %
#141
1"
b11110 !
b11100101 '
b111001 &
b11001010 %
#142
0"
b11001100 !
b101011 '
b10100001 &
b100011110 %
#143
1"
b1001001 !
b11001000 '
b10000001 &
b11001100 %
#144
0"
b11001000 !
b10100001 '
b100111 &
b101001001 %
#145
b100011 !
b100 '
b11111 &
b11001000 %
#146
b11101110 !
b10010110 '
b1011000 &
b100011 %
#147
b100110 !
b10010 '
b10100 &
b11101110 %
#148
1"
b1000111 !
b10110001 '
b10010110 &
b100110 %
#149
b1000010 !
b11101101 '
b1010101 &
b101000111 %
#150
b100000 !
b11110101 '
b101011 &
b101000010 %
#151
0"
b11010100 !
b100111 '
b10101101 &
b100100000 %
#152
1"
b101011 !
b10100111 '
b10000100 &
b11010100 %
#153
b10100000 !
b10111001 '
b11100111 &
b100101011 %
#154
b100100 !
b11011011 '
b1001001 &
b110100000 %
#155
b11010 !
b1010001 '
b11001001 &
b100100100 %
#156
0"
b11001011 !
b101010 '
b10100001 &
b100011010 %
#157
1"
b111111 !
b1000101 '
b11111010 &
b11001011 %
#158
0"
b11111111 !
b1111100 '
b10000011 &
b100111111 %
#159
1"
b1110000 !
b11111110 '
b1110010 &
b11111111 %
#160
0"
b11010111 !
b1101111 '
b1101000 &
b101110000 %
#161
1"
b1110110 !
b11110000 '
b10000110 &
b11010111 %
#162
0"
b1111000 !
b1000000 '
b111000 &
b101110110 %
#163
1"
b11110 !
b11110110 '
b101000 &
b1111000 %
#164
b10000101 !
b11000000 '
b11000101 &
b100011110 %
#165
0"
b10101101 !
b111001 '
b1110100 &
b110000101 %
#166
b11101100 !
b111100 '
b10110000 &
b10101101 %
#167
b10001100 !
b1100010 '
b101010 &
b11101100 %
#168
b11110110 !
b11100001 '
b10101 &
b10001100 %
#169
b1011010 !
b1000011 '
b10111 &
b11110110 %
#170
1"
b1001111 !
b10000110 '
b11001001 &
b1011010 %
#171
0"
b11100110 !
b11000001 '
b100101 &
b101001111 %
#172
b11100111 !
b1011010 '
b10001101 &
b11100110 %
#173
b110011 !
b101100 '
b111 &
b11100111 %
#174
b1111101 !
b1110001 '
b1100 &
b110011 %
#175
b11110001 !
b10110110 '
b111011 &
b1111101 %
#176
1"
b10010101 !
b10011110 '
b11110111 &
b11110001 %
#177
0"
b10110001 !
b1010101 '
b1011100 &
b110010101 %
#178
b11000000 !
b10100000 '
b100000 &
b10110001 %
#179
1"
b100110 !
b10110100 '
b1110010 &
b11000000 %
#180
0"
b11101010 !
b1101 '
b11011101 &
b100100110 %
#181
b11000100 !
b1111001 '
b1001011 &
b11101010 %
#182
1"
b10011011 !
b11111101 '
b10011110 &
b11000100 %
#183
b1010 !
b10001111 '
b1111011 &
b110011011 %
#184
0"
b11100110 !
b11100011 '
b11 &
b100001010 %
#185
b11001110 !
b10110001 '
b11101 &
b11100110 %
#186
b11011001 !
b10010101 '
b1000100 &
b11001110 %
#187
1"
b11001101 !
b11101101 '
b11100000 &
b11011001 %
#188
b1001010 !
b11111000 '
b1010010 &
b111001101 %
#189
0"
b11011111 !
b1010010 '
b10001101 &
b101001010 %
#190
b11001010 !
b1000110 '
b10000100 &
b11011111 %
#191
1"
b11100 !
b10010000 '
b10001100 &
b11001010 %
#192
0"
b10000001 !
b1101010 '
b10111 &
b100011100 %
#193
1"
b101110 !
b10101010 '
b10000100 &
b10000001 %
#194
0"
b11011100 !
b1100000 '
b1111100 &
b100101110 %
#195
1"
b1000101 !
b10001011 '
b10111010 &
b11011100 %
#196
0"
b11001011 !
b100101 '
b10100110 &
b101000101 %
#197
b11010100 !
b10100010 '
b110010 &
b11001011 %
#198
b1011101 !
b10100 '
b1001001 &
b11010100 %
#199
b10001000 !
b1001011 '
b111101 &
b1011101 %
#200
b10100011 !
b1000111 '
b1011100 &
b10001000 %
#201
b10111111 !
b111001 '
b10000110 &
b10100011 %
#202
1"
b10000100 !
b11010000 '
b10110100 &
b10111111 %
#203
0"
b10111000 !
b10001100 '
b101100 &
b110000100 %
#204
b1110001 !
b1101010 '
b111 &
b10111000 %
#205
b11111001 !
b11101000 '
b10001 &
b1110001 %
#206
b10111110 !
b1110011 '
b1001011 &
b11111001 %
#207
1"
b1111 !
b100011 '
b11101100 &
b10111110 %
#208
b1101101 !
b11001001 '
b10100100 &
b100001111 %
#209
b11000 !
b11011111 '
b111001 &
b101101101 %
#210
b111011 !
b1100111 '
b11010100 &
b100011000 %
#211
b1001101 !
b10110000 '
b10011101 &
b100111011 %
#212
0"
b11001011 !
b1001001 '
b10000010 &
b101001101 %
#213
b11111001 !
b100000 '
b11011001 &
b11001011 %
#214
b10101111 !
b10010011 '
b11100 &
b11111001 %
#215
1"
b1101 !
b101010 '
b11100011 &
b10101111 %
#216
b100101 !
b1011101 '
b11001000 &
b100001101 %
#217
0"
b10111110 !
b10000100 '
b111010 &
b100100101 %
#218
b1100100 !
b111001 '
b101011 &
b10111110 %
#219
b1010010 '
b10010 &
b1100100 %
#220
1"
b101001 !
b11010000 '
b1011001 &
#221
b101 !
b10010111 '
b1101110 &
b100101001 %
#222
b10000001 !
b10100110 '
b11011011 &
b100000101 %
#223
0"
b10111011 !
b0 '
b10111011 &
b110000001 %
#224
b1111000 !
b1101001 '
b1111 &
b10111011 %
#225
b1100101 !
b1011001 '
b1100 &
b1111000 %
#226
1"
b10010100 !
b11001111 '
b11000101 &
b1100101 %
#227
0"
b11100001 !
b1010001 '
b10010000 &
b110010100 %
#228
b11100000 !
b1110111 '
b1101001 &
b11100001 %
#229
1"
b100010 !
b11011000 '
b1001010 &
b11100000 %
#230
b1011111 !
b11000100 '
b10011011 &
b100100010 %
#231
b1101111 !
b10110111 '
b10111000 &
b101011111 %
#232
0"
b10110110 !
b110000 '
b10000110 &
b101101111 %
#233
1"
b101100 !
b10110101 '
b1110111 &
b10110110 %
#234
0"
b11011011 !
b111 '
b11010100 &
b100101100 %
#235
1"
b1011111 !
b11101001 '
b1110110 &
b11011011 %
#236
0"
b10001100 !
b1 '
b10001011 &
b101011111 %
#237
1"
b1011011 !
b10000000 '
b11011011 &
b10001100 %
#238
b10000111 !
b11000101 '
b11000010 &
b101011011 %
#239
0"
b11011111 !
b10101111 '
b110000 &
b110000111 %
#240
1"
b10101 !
b1100110 &
b11011111 %
#241
b11100001 !
b11111000 '
b11101001 &
b100010101 %
#242
0"
b11110101 !
b11101111 '
b110 &
b111100001 %
#243
1"
b1110110 !
b10010101 '
b11100001 &
b11110101 %
#244
b1001110 !
b1100000 '
b11101110 &
b101110110 %
#245
b1101 !
b101000 '
b11100101 &
b101001110 %
#246
0"
b10001101 !
b101001 '
b1100100 &
b100001101 %
#247
1"
b1011000 !
b1110111 '
b11100001 &
b10001101 %
#248
0"
b11101111 !
b10000001 '
b1101110 &
b101011000 %
#249
1"
b111101 !
b1101000 '
b11010101 &
b11101111 %
#250
b10011010 !
b10101010 '
b11110000 &
b100111101 %
#251
b0 !
b11110001 '
b1111 &
b110011010 %
#252
b1011 !
b10001110 '
b1111101 &
b100000000 %
#253
b11110 !
b111100 '
b11100010 &
b100001011 %
#254
b10011000 !
b11101111 '
b10101001 &
b100011110 %
#255
b1010 !
b10101111 '
b1011011 &
b110011000 %
#256
b11 !
b10111001 '
b1001010 &
b100001010 %
#257
0"
b100110 !
b10011 '
b10011 &
b100000011 %
#258
b10110110 !
b1010001 '
b1100101 &
b100110 %
#259
1"
b1010000 !
b10011001 '
b10110111 &
b10110110 %
#260
0"
b10101011 !
b1110001 '
b111010 &
b101010000 %
#261
1"
b1000110 !
b11100100 '
b1100010 &
b10101011 %
#262
0"
b10100111 !
b1111101 '
b101010 &
b101000110 %
#263
1"
b111110 !
b11100101 '
b1011001 &
b10100111 %
#264
b10110110 !
b11001001 '
b11101101 &
b100111110 %
#265
0"
b11110000 !
b10101111 '
b1000001 &
b110110110 %
#266
1"
b10101000 !
b11001101 '
b11011011 &
b11110000 %
#267
0"
b1110110 !
b110 '
b1110000 &
b110101000 %
#268
1"
b1011111 !
b10111101 '
b10100010 &
b1110110 %
#269
b1000110 !
b11011100 '
b1101010 &
b101011111 %
#270
0"
b11001011 !
b1111011 '
b1010000 &
b101000110 %
#271
b10011101 !
b1111000 '
b100101 &
b11001011 %
#272
1"
b1010010 !
b1011100 '
b11110110 &
b10011101 %
#273
0"
b10011100 !
b1111001 '
b100011 &
b101010010 %
#274
1"
b10000011 !
b10111011 '
b11001000 &
b10011100 %
#275
0"
b10000001 !
b1110011 '
b1110 &
b110000011 %
#276
b11011010 !
b11001110 '
b1100 &
b10000001 %
#277
1"
b101101 !
b1011001 '
b11010100 &
b11011010 %
#278
b1101100 !
b10110011 '
b10111001 &
b100101101 %
#279
b1101001 !
b1110101 '
b11110100 &
b101101100 %
#280
0"
b1000101 !
b111001 '
b1100 &
b101101001 %
#281
b10111 !
b10101 '
b10 &
b1000101 %
#282
b1010011 !
b1001110 '
b101 &
b10111 %
#283
b10111010 !
b10111000 '
b10 &
b1010011 %
#284
b10010101 !
b10001101 '
b1000 &
b10111010 %
#285
1"
b10010111 !
b11101000 '
b10101111 &
b10010101 %
#286
b10000101 !
b11110101 '
b10010000 &
b110010111 %
#287
0"
b11000111 !
b1111011 '
b1001100 &
b110000101 %
#288
b1100101 !
b100101 '
b1000000 &
b11000111 %
#289
b1111101 !
b1110000 '
b1101 &
b1100101 %
#290
b1010110 !
b101001 '
b101101 &
b1111101 %
#291
b11101100 !
b110000 '
b10111100 &
b1010110 %
#292
1"
b10000 !
b1010000 '
b11000000 &
b11101100 %
#293
0"
b11101110 !
b1001101 '
b10100001 &
b100010000 %
#294
1"
b11101010 !
b11110101 '
b11110101 &
b11101110 %
#295
0"
b11110001 !
b10010100 '
b1011101 &
b111101010 %
#296
1"
b100110 !
b10111100 '
b1101010 &
b11110001 %
#297
b1010110 !
b10011110 '
b10111000 &
b100100110 %
#298
b1000000 !
b1000110 '
b11111010 &
b101010110 %
#299
0"
b10011010 !
b10010011 '
b111 &
b101000000 %
#300
1"
b1100 !
b10110111 '
b1010101 &
b10011010 %
#301
0"
b10101000 !
b1100011 '
b1000101 &
b100001100 %
#302
b1111111 !
b100110 '
b1011001 &
b10101000 %
#303
b10000110 !
b11110 '
b1101000 &
b1111111 %
#304
b11101010 !
b1011010 '
b10010000 &
b10000110 %
#305
b11010101 !
b10111001 '
b11100 &
b11101010 %
#306
1"
b1111011 !
b11010000 '
b10101011 &
b11010101 %
#307
b1000111 !
b11011000 '
b1101111 &
b101111011 %
#308
0"
b11010010 !
b10001101 '
b1000101 &
b101000111 %
#309
1"
b10000111 !
b11111100 '
b10001011 &
b11010010 %
#310
b10000000 !
b10100100 '
b11011100 &
b110000111 %
#311
0"
b10111110 !
b10100101 '
b11001 &
b110000000 %
#312
1"
b110001 !
b11110011 '
b111110 &
b10111110 %
#313
b11100 !
b11000100 '
b1011000 &
b100110001 %
#314
0"
b1100010 !
b110 '
b1011100 &
b100011100 %
#315
b10110010 !
b11000 '
b10011010 &
b1100010 %
#316
1"
b1101111 !
b10101010 '
b11000101 &
b10110010 %
#317
0"
b11011101 !
b11000011 '
b11010 &
b101101111 %
#318
b10111110 !
b1100 '
b10110010 &
b11011101 %
#319
1"
b10101100 !
b11000011 '
b11101001 &
b10111110 %
#320
b11100011 !
b11111000 '
b11101011 &
b110101100 %
#321
b1111011 !
b10001001 '
b11110010 &
b111100011 %
#322
0"
b10001010 !
b11011 '
b1101111 &
b101111011 %
#323
1"
b10101 !
b1101000 '
b10101101 &
b10001010 %
#324
0"
b11110100 !
b11001111 '
b100101 &
b100010101 %
#325
b11000110 !
b11011 '
b10101011 &
b11110100 %
#326
b11011101 !
b1011101 '
b10000000 &
b11000110 %
#327
b10000110 !
b100 '
b10000010 &
b11011101 %
#328
b10001101 !
b110110 '
b1010111 &
b10000110 %
#329
b10101011 !
b1111001 '
b110010 &
b10001101 %
#330
b11111010 !
b10110 '
b11100100 &
b10101011 %
#331
1"
b1101010 !
b11000000 '
b10101010 &
b11111010 %
#332
0"
b10111010 !
b10001100 '
b101110 &
b101101010 %
#333
1"
b1101100 !
b11111011 '
b1110001 &
b10111010 %
#334
b10011000 !
b11011100 '
b10111100 &
b101101100 %
#335
0"
b11011000 !
b11000001 '
b10111 &
b110011000 %
#336
1"
b10100000 !
b10110101 '
b11101011 &
b11011000 %
#337
b11000 !
b10001111 '
b10001001 &
b110100000 %
#338
b1101111 !
b10110000 '
b10111111 &
b100011000 %
#339
b10101001 !
b11010110 '
b11010011 &
b101101111 %
#340
0"
b10011100 !
b11010 '
b10000010 &
b110101001 %
#341
1"
b1001000 !
b11010111 '
b1110001 &
b10011100 %
#342
0"
b11111111 !
b11110001 '
b1110 &
b101001000 %
#343
b11010010 !
b101 '
b11001101 &
b11111111 %
#344
b10110100 !
b10011000 '
b11100 &
b11010010 %
#345
1"
b10110 !
b101010 '
b11101100 &
b10110100 %
#346
0"
b10011100 !
b110111 '
b1100101 &
b100010110 %
#347
1"
b1 !
b11111110 '
b11 &
b10011100 %
#348
b111011 !
b111110 '
b11111101 &
b100000001 %
#349
b1011100 !
b1110100 '
b11101000 &
b100111011 %
#350
0"
b10110110 !
b110 '
b10110000 &
b101011100 %
#351
b1111010 !
b1101000 '
b10010 &
b10110110 %
#352
1"
b11000011 !
b11111110 '
b11000101 &
b1111010 %
#353
b101001 !
b11110011 '
b110110 &
b111000011 %
#354
b1100110 !
b1101011 '
b11111011 &
b100101001 %
#355
0"
b100110 !
b1111 '
b10111 &
b101100110 %
#356
b111110 !
b101010 '
b10100 &
b100110 %
#357
1"
b1111010 !
b11010100 '
b10100110 &
b111110 %
#358
b110110 !
b1101011 '
b11001011 &
b101111010 %
#359
0"
b11111000 !
b11110100 '
b100 &
b100110110 %
#360
1"
b1101110 !
b11100001 '
b10001101 &
b11111000 %
#361
b111110 !
b10111001 '
b10000101 &
b101101110 %
#362
b101001 !
b1100000 '
b11001001 &
b100111110 %
#363
0"
b10000010 !
b111100 '
b1000110 &
b100101001 %
#364
b10001111 !
b1011000 '
b110111 &
b10000010 %
#365
b10000001 !
b1110 '
b1110011 &
b10001111 %
#366
1"
b1100 !
b110000 '
b11011100 &
b10000001 %
#367
0"
b11010000 !
b0 '
b11010000 &
b100001100 %
#368
1"
b111011 !
b11111000 '
b1000011 &
b11010000 %
#369
0"
b11110100 !
b1010011 '
b10100001 &
b100111011 %
#370
b11110111 !
b1011111 '
b10011000 &
b11110100 %
#371
1"
b10000001 !
b11111010 '
b10000111 &
b11110111 %
#372
0"
b10011101 !
b1110000 '
b101101 &
b110000001 %
#373
b10011100 !
b110001 '
b1101011 &
b10011101 %
#374
b11110 !
b1100 '
b10010 &
b10011100 %
#375
b100010 !
b10101 '
b1101 &
b11110 %
#376
b11010100 !
b10010100 '
b1000000 &
b100010 %
#377
b10000000 '
b1010100 &
b11010100 %
#378
b11010110 !
b11000011 '
b10011 &
#379
1"
b11001001 !
b11011100 '
b11101101 &
b11010110 %
#380
0"
b10011111 !
b100111 '
b1111000 &
b111001001 %
#381
b10000010 !
b100011 '
b1011111 &
b10011111 %
#382
b11100011 !
b111000 '
b10101011 &
b10000010 %
#383
b11101011 !
b11001001 '
b100010 &
b11100011 %
#384
1"
b1001001 !
b10000010 '
b11000111 &
b11101011 %
#385
b10010101 !
b11000111 '
b11001110 &
b101001001 %
#386
0"
b11111111 !
b11011011 '
b100100 &
b110010101 %
#387
b1111101 !
b1110101 '
b1000 &
b11111111 %
#388
b11001111 !
b11010 '
b10110101 &
b1111101 %
#389
b10111010 !
b10000010 '
b111000 &
b11001111 %
#390
b10101000 !
b1010000 '
b1011000 &
b10111010 %
#391
1"
b1000111 !
b10100100 '
b10100011 &
b10101000 %
#392
b1001111 !
b11101010 '
b1100101 &
b101000111 %
#393
0"
b1011010 !
b1010100 '
b110 &
b101001111 %
#394
1"
b100011 !
b11001000 '
b1011011 &
b1011010 %
#395
0"
b1111111 !
b110111 '
b1001000 &
b100100011 %
#396
1"
b10101101 !
b10110101 '
b11111000 &
b1111111 %
#397
0"
b11010100 !
b10000011 '
b1010001 &
b110101101 %
#398
b11010000 !
b110101 '
b10011011 &
b11010100 %
#399
1"
b10101011 !
b11111011 '
b10110000 &
b11010000 %
#400
0"
b1111111 !
b110000 '
b1001111 &
b110101011 %
#401
b11110101 !
b11011101 '
b11000 &
b1111111 %
#402
b10100111 !
b1100001 '
b1000110 &
b11110101 %
#403
b10101110 !
b1010101 '
b1011001 &
b10100111 %
#404
b111010 !
b1011 '
b101111 &
b10101110 %
#405
1"
b10110001 !
b11010011 '
b11011110 &
b111010 %
#406
b10001 !
b11101001 '
b101000 &
b110110001 %
#407
b101101 !
b11010101 '
b1011000 &
b100010001 %
#408
b10010111 !
b11010100 '
b11000011 &
b100101101 %
#409
b100010 !
b1111110 '
b10100100 &
b110010111 %
#410
0"
b11100101 !
b1111 '
b11010110 &
b100100010 %
#411
1"
b100011 !
b10100000 '
b10000011 &
b11100101 %
#412
b1000001 !
b10111111 '
b10000010 &
b100100011 %
#413
0"
b10111100 !
b1110111 '
b1000101 &
b101000001 %
#414
b10111010 !
b1110101 '
b10111100 %
#415
1"
b10111110 !
b11000110 '
b11111000 &
b10111010 %
#416
0"
b10111100 !
b1010000 '
b1101100 &
b110111110 %
#417
b11001101 !
b10011100 '
b110001 &
b10111100 %
#418
1"
b1101011 !
b10101111 '
b10111100 &
b11001101 %
#419
0"
b1110111 !
b1101001 '
b1110 &
b101101011 %
#420
1"
b10010000 !
b11011110 '
b10110010 &
b1110111 %
#421
b101111 !
b10101010 '
b10000101 &
b110010000 %
#422
0"
b11101010 !
b11000010 '
b101000 &
b100101111 %
#423
1"
b1101101 !
b11010011 '
b10011010 &
b11101010 %
#424
b10110101 !
b11111011 '
b10111010 &
b101101101 %
#425
b1001101 !
b11000010 '
b10001011 &
b110110101 %
#426
b111101 !
b1110001 '
b11001100 &
b101001101 %
#427
0"
b11111111 !
b1100001 '
b10011110 &
b100111101 %
#428
1"
b111010 !
b10111111 '
b1111011 &
b11111111 %
#429
b1010001 !
b11000000 '
b10010001 &
b100111010 %
#430
0"
b11010111 !
b1111110 '
b1011001 &
b101010001 %
#431
b10100101 !
b1010001 '
b1010100 &
b11010111 %
#432
1"
b110000 !
b11100111 '
b1001001 &
b10100101 %
#433
0"
b10100111 !
b10000011 '
b100100 &
b100110000 %
#434
1"
b10100 !
b10111001 '
b1011011 &
b10100111 %
#435
b1100 !
b1110111 '
b10010101 &
b100010100 %
#436
b11010111 !
b11100110 '
b11110001 &
b100001100 %
#437
0"
b10110011 !
b100 '
b10101111 &
b111010111 %
#438
1"
b1110 !
b11111100 '
b10010 &
b10110011 %
#439
b1101111 !
b11000100 '
b10101011 &
b100001110 %
#440
b1 !
b11000010 '
b111111 &
b101101111 %
